JianZhiQianduanOffer/README.md
JianZhiQianduanOffer/__init__.py
JianZhiQianduanOffer/__main__.py
JianZhiQianduanOffer/file.epub
JianZhiQianduanOffer/index.html
JianZhiQianduanOffer/css/__init__.py
JianZhiQianduanOffer/css/annotations.css
JianZhiQianduanOffer/css/main.css
JianZhiQianduanOffer/css/normalize.css
JianZhiQianduanOffer/css/popup.css
JianZhiQianduanOffer/font/__init__.py
JianZhiQianduanOffer/font/fontello.eot
JianZhiQianduanOffer/font/fontello.svg
JianZhiQianduanOffer/font/fontello.ttf
JianZhiQianduanOffer/font/fontello.woff
JianZhiQianduanOffer/img/__init__.py
JianZhiQianduanOffer/img/annotator-glyph-sprite.png
JianZhiQianduanOffer/img/annotator-icon-sprite.png
JianZhiQianduanOffer/img/apple-touch-icon.png
JianZhiQianduanOffer/img/cancelfullscreen.png
JianZhiQianduanOffer/img/close.png
JianZhiQianduanOffer/img/fullscreen.png
JianZhiQianduanOffer/img/loader.gif
JianZhiQianduanOffer/img/menu-icon.png
JianZhiQianduanOffer/img/save.png
JianZhiQianduanOffer/img/saved.png
JianZhiQianduanOffer/img/settings-s.png
JianZhiQianduanOffer/img/settings.png
JianZhiQianduanOffer/img/star.png
JianZhiQianduanOffer/js/__init__.py
JianZhiQianduanOffer/js/epub.js
JianZhiQianduanOffer/js/epub.min.js
JianZhiQianduanOffer/js/epub.min.map
JianZhiQianduanOffer/js/hooks.min.js
JianZhiQianduanOffer/js/hooks.min.map
JianZhiQianduanOffer/js/reader.js
JianZhiQianduanOffer/js/reader.js.map
JianZhiQianduanOffer/js/reader.min.js
JianZhiQianduanOffer/js/reader.min.map
JianZhiQianduanOffer/js/hooks/__init__.py
JianZhiQianduanOffer/js/hooks/extensions/__init__.py
JianZhiQianduanOffer/js/hooks/extensions/highlight.js
JianZhiQianduanOffer/js/libs/__init__.py
JianZhiQianduanOffer/js/libs/jquery.min.js
JianZhiQianduanOffer/js/libs/localforage.min.js
JianZhiQianduanOffer/js/libs/screenfull.js
JianZhiQianduanOffer/js/libs/screenfull.min.js
JianZhiQianduanOffer/js/libs/zip.min.js
JianZhiQianduanOffer/js/plugins/__init__.py
JianZhiQianduanOffer/js/plugins/hypothesis.js
jian_zhi_qianduan_offer-2024.3.5.0.dist-info/METADATA
jian_zhi_qianduan_offer-2024.3.5.0.dist-info/WHEEL
jian_zhi_qianduan_offer-2024.3.5.0.dist-info/entry_points.txt
jian_zhi_qianduan_offer-2024.3.5.0.dist-info/top_level.txt
jian_zhi_qianduan_offer-2024.3.5.0.dist-info/RECORD
